m2p/__init__.py
m2p/_version.py
m2p/monomers.py
m2p/polyestimator.py
m2p/polymaker.py
m2p/stereo_reactions.py
m2p/utils.py
m2p-0.1.8.1.dist-info/LICENSE
m2p-0.1.8.1.dist-info/METADATA
m2p-0.1.8.1.dist-info/WHEEL
m2p-0.1.8.1.dist-info/top_level.txt
m2p-0.1.8.1.dist-info/RECORD
