Metadata-Version: 2.1
Name: m2p
Version: 0.1.8.1
Summary: Library for creating polymer structures from monomers using SMILES strings
Home-page: https://github.com/NREL/m2p
Author: Nolan Wilson
Author-email: nolan.wilson@nrel.gov
Project-URL: Source, https://github.com/NREL/m2p
Classifier: Development Status :: 3 - Alpha
Classifier: Intended Audience :: Developers
Classifier: License :: OSI Approved :: BSD License
Classifier: Programming Language :: Python :: 3
Classifier: Programming Language :: Python :: 3.8
License-File: LICENSE
Requires-Dist: pandas
Requires-Dist: tqdm
Requires-Dist: numpy
Requires-Dist: casadi
Provides-Extra: test
Requires-Dist: pytest ; extra == 'test'
